setup.py
nefertari_mongodb/__init__.py
nefertari_mongodb/documents.py
nefertari_mongodb/fields.py
nefertari_mongodb/metaclasses.py
nefertari_mongodb/serializers.py
nefertari_mongodb/signals.py
nefertari_mongodb/utils.py
nefertari_mongodb.egg-info/PKG-INFO
nefertari_mongodb.egg-info/SOURCES.txt
nefertari_mongodb.egg-info/dependency_links.txt
nefertari_mongodb.egg-info/not-zip-safe
nefertari_mongodb.egg-info/pbr.json
nefertari_mongodb.egg-info/requires.txt
nefertari_mongodb.egg-info/top_level.txt
nefertari_mongodb/tests/__init__.py
nefertari_mongodb/tests/test_documents.py