Metadata-Version: 1.1
Name: nefertari-mongodb
Version: 0.3.3
Summary: mongodb engine for nefertari
Home-page: https://github.com/brandicted/nefertari-mongodb
Author: Brandicted
Author-email: hello@brandicted.com
License: UNKNOWN
Keywords: web wsgi bfg pylons pyramid rest mongodb mongoengine
Platform: UNKNOWN
Classifier: Programming Language :: Python
Classifier: Programming Language :: Python :: 2
Classifier: Programming Language :: Python :: 2.7
Classifier: Programming Language :: Python :: 3
Classifier: Programming Language :: Python :: 3.4
Classifier: Framework :: Pyramid
Classifier: Topic :: Internet :: WWW/HTTP
Classifier: Topic :: Internet :: WWW/HTTP :: WSGI :: Application
Classifier: Topic :: Database
Classifier: Topic :: Database :: Database Engines/Servers
